ietf_comments_engine/__init__.py
ietf_comments_engine/changes.py
ietf_comments_engine/md_comments.py
ietf_comments_engine/py.typed
ietf_comments_engine/types.py
ietf_comments_engine/util.py
ietf_comments_engine/xml_comments.py
ietf_comments_engine-0.1.4.dist-info/LICENSE
ietf_comments_engine-0.1.4.dist-info/METADATA
ietf_comments_engine-0.1.4.dist-info/WHEEL
ietf_comments_engine-0.1.4.dist-info/top_level.txt
ietf_comments_engine-0.1.4.dist-info/RECORD
