Metadata-Version: 2.1
Name: ietf-comments-engine
Version: 0.1.4
Summary: DESCRIPTION
Author-email: Mark Nottingham <mnot@mnot.net>
Project-URL: homepage, https://github.com/mnot/ietf-comments-engine
Classifier: Operating System :: OS Independent
Classifier: Development Status :: 4 - Beta
Classifier: License :: OSI Approved :: MIT License
Requires-Python: >=3.9
License-File: LICENSE
Requires-Dist: commonmark
Provides-Extra: dev
Requires-Dist: mypy ; extra == 'dev'
Requires-Dist: black ; extra == 'dev'
Requires-Dist: pylint ; extra == 'dev'
Requires-Dist: pytest ; extra == 'dev'
Requires-Dist: pytest-md ; extra == 'dev'
Requires-Dist: validate-pyproject ; extra == 'dev'
Requires-Dist: build ; extra == 'dev'
Requires-Dist: types-commonmark ; extra == 'dev'
